showpkg.py
showpkg-0.0.1.dist-info/DESCRIPTION.rst
showpkg-0.0.1.dist-info/METADATA
showpkg-0.0.1.dist-info/metadata.json
showpkg-0.0.1.dist-info/RECORD
showpkg-0.0.1.dist-info/top_level.txt
showpkg-0.0.1.dist-info/WHEEL
