Metadata-Version: 2.0
Name: showpkg
Version: 0.0.1
Summary: Show package info
Home-page: http://github.com/minrk/showpkg
Author: Min Ragan-Kelley
Author-email: benjaminrk@gmail.com
License: BSD
Platform: UNKNOWN
Classifier: License :: OSI Approved :: BSD License
Classifier: Operating System :: MacOS :: MacOS X
Classifier: Programming Language :: Python :: 2
Classifier: Programming Language :: Python :: 2.7
Classifier: Programming Language :: Python :: 3
Classifier: Programming Language :: Python :: 3.4
Classifier: Programming Language :: Python :: 3.5
